user_management/__init__.py
user_management/config.py
user_management/clients/__init__.py
user_management/clients/firebase_client.py
user_management/clients/stripe_client.py
user_management/clients/db_clients/__init__.py
user_management/clients/db_clients/customer_client.py
user_management/clients/db_clients/product_client.py
user_management/clients/db_clients/subscription_client.py
user_management/clients/db_clients/user_client.py
user_management/models/__init__.py
user_management/models/customer.py
user_management/models/product.py
user_management/models/subscription.py
user_management/models/user.py
user_management-0.5.4.dist-info/LICENSE
user_management-0.5.4.dist-info/METADATA
user_management-0.5.4.dist-info/WHEEL
user_management-0.5.4.dist-info/top_level.txt
user_management-0.5.4.dist-info/RECORD
