Metadata-Version: 2.2
Name: user-management
Version: 0.5.4
Summary: A user management package using Firebase
Home-page: https://github.com/clickstack/user-management
Author: Brennen
Author-email: brennen.barney@gmail.com
Classifier: Programming Language :: Python :: 3
Classifier: License :: OSI Approved :: MIT License
Classifier: Operating System :: OS Independent
Requires-Python: >=3.9
License-File: LICENSE
Requires-Dist: firebase-admin>=6.4.0
Requires-Dist: pydantic>=2.0.0
Requires-Dist: python-jose[cryptography]>=3.3.0
Requires-Dist: boto3>=1.34.0
Requires-Dist: stripe>=7.10.0
Dynamic: author
Dynamic: author-email
Dynamic: classifier
Dynamic: description
Dynamic: description-content-type
Dynamic: home-page
Dynamic: requires-dist
Dynamic: requires-python
Dynamic: summary
